MANIFEST.in
README.rst
pyvenv.cfg
setup.cfg
setup.py
test.py
docs/COPYRIGHT.rst
docs/CREDITS.rst
docs/HISTORY.rst
src/horseman/__init__.py
src/horseman/http.py
src/horseman/mapping.py
src/horseman/meta.py
src/horseman/response.py
src/horseman/types.py
src/horseman.egg-info/PKG-INFO
src/horseman.egg-info/SOURCES.txt
src/horseman.egg-info/dependency_links.txt
src/horseman.egg-info/not-zip-safe
src/horseman.egg-info/requires.txt
src/horseman.egg-info/top_level.txt
src/horseman/parsers/__init__.py
src/horseman/parsers/multipart.py
tests/test_apiview.py
tests/test_content_type.py
tests/test_cookies.py
tests/test_httperrors.py
tests/test_mapping.py
tests/test_nodes.py
tests/test_parser.py
tests/test_response.py
tests/test_response_headers.py
tests/parsing/test_json.py
tests/parsing/test_multipart.py
tests/parsing/test_urlencoded.py