Metadata-Version: 2.1
Name: horseman
Version: 0.6
Summary: Toolkit to build headless WSGI applications.
Home-page: http://pypi.python.org/pypi/horseman
Author: Souheil Chelfouh
Author-email: trollfot@gmail.com
Maintainer: Souheil Chelfouh
Maintainer-email: trollfot@gmail.com
License: BSD-3-Clause
Project-URL: Source Code, https://github.com/HorsemanWSGI/horseman
Platform: UNKNOWN
Classifier: Development Status :: 4 - Beta
Classifier: Environment :: Web Environment
Classifier: Intended Audience :: Developers
Classifier: License :: OSI Approved :: BSD License
Classifier: Programming Language :: Python :: 3.8
Classifier: Programming Language :: Python :: 3.9
Classifier: Programming Language :: Python :: 3.10
Classifier: Topic :: Internet :: WWW/HTTP :: WSGI
Requires-Python: >=3.8
Provides-Extra: test
